hf_datasets-0.3.0.data/scripts/nlp-cli
nlp/__init__.py
nlp/arrow_dataset.py
nlp/arrow_reader.py
nlp/arrow_writer.py
nlp/builder.py
nlp/features.py
nlp/hf_api.py
nlp/info.py
nlp/inspect.py
nlp/load.py
nlp/metric.py
nlp/naming.py
nlp/search.py
nlp/splits.py
nlp/commands/__init__.py
nlp/commands/convert.py
nlp/commands/download.py
nlp/commands/dummy_data.py
nlp/commands/env.py
nlp/commands/run_beam.py
nlp/commands/test.py
nlp/commands/user.py
nlp/datasets/__init__.py
nlp/datasets/trec/__init__.py
nlp/datasets/trec/8d17af785ebd9dc949a67d11d062a6610cc4d60bd96fce7538adf5c01f5f56e0/__init__.py
nlp/datasets/trec/8d17af785ebd9dc949a67d11d062a6610cc4d60bd96fce7538adf5c01f5f56e0/trec.py
nlp/datasets/trec/fa5fb29bbccaaec6b8eee795b49802ded5a0b23521aeed9159f948b9566956e2/__init__.py
nlp/datasets/trec/fa5fb29bbccaaec6b8eee795b49802ded5a0b23521aeed9159f948b9566956e2/trec.py
nlp/metrics/__init__.py
nlp/utils/__init__.py
nlp/utils/beam_utils.py
nlp/utils/download_manager.py
nlp/utils/file_utils.py
nlp/utils/info_utils.py
nlp/utils/mock_download_manager.py
nlp/utils/py_utils.py
nlp/utils/tqdm_utils.py
nlp/utils/version.py
hf_datasets-0.3.0.dist-info/AUTHORS
hf_datasets-0.3.0.dist-info/LICENSE
hf_datasets-0.3.0.dist-info/METADATA
hf_datasets-0.3.0.dist-info/WHEEL
hf_datasets-0.3.0.dist-info/top_level.txt
hf_datasets-0.3.0.dist-info/RECORD
