Metadata-Version: 2.1
Name: hf-datasets
Version: 0.3.0
Summary: HuggingFace/NLP is an open library of NLP datasets.
Home-page: https://github.com/huggingface/nlp
Author: HuggingFace Inc.
Author-email: thomas@huggingface.co
License: Apache 2.0
Download-URL: https://github.com/huggingface/nlp/tags
Keywords: nlp machine learning datasets metrics
Platform: UNKNOWN
Classifier: Development Status :: 5 - Production/Stable
Classifier: Intended Audience :: Developers
Classifier: Intended Audience :: Education
Classifier: Intended Audience :: Science/Research
Classifier: License :: OSI Approved :: Apache Software License
Classifier: Operating System :: OS Independent
Classifier: Programming Language :: Python :: 3
Classifier: Programming Language :: Python :: 3.6
Classifier: Programming Language :: Python :: 3.7
Classifier: Topic :: Scientific/Engineering :: Artificial Intelligence
Requires-Dist: numpy
Requires-Dist: pyarrow (>=0.16.0)
Requires-Dist: dill
Requires-Dist: pandas
Requires-Dist: requests (>=2.19.0)
Requires-Dist: tqdm (>=4.27)
Requires-Dist: filelock
Requires-Dist: dataclasses ; python_version < "3.7"
Provides-Extra: apache-beam
Requires-Dist: apache-beam ; extra == 'apache-beam'
Provides-Extra: dev
Requires-Dist: apache-beam ; extra == 'dev'
Requires-Dist: absl-py ; extra == 'dev'
Requires-Dist: bs4 ; extra == 'dev'
Requires-Dist: elasticsearch ; extra == 'dev'
Requires-Dist: faiss-cpu ; extra == 'dev'
Requires-Dist: langdetect ; extra == 'dev'
Requires-Dist: mwparserfromhell ; extra == 'dev'
Requires-Dist: nltk ; extra == 'dev'
Requires-Dist: pytest ; extra == 'dev'
Requires-Dist: pytest-xdist ; extra == 'dev'
Requires-Dist: tensorflow ; extra == 'dev'
Requires-Dist: torch ; extra == 'dev'
Requires-Dist: tldextract ; extra == 'dev'
Requires-Dist: zstandard ; extra == 'dev'
Requires-Dist: black ; extra == 'dev'
Requires-Dist: isort ; extra == 'dev'
Requires-Dist: flake8 (==3.7.9) ; extra == 'dev'
Provides-Extra: quality
Requires-Dist: black ; extra == 'quality'
Requires-Dist: isort ; extra == 'quality'
Requires-Dist: flake8 (==3.7.9) ; extra == 'quality'
Provides-Extra: tensorflow
Requires-Dist: tensorflow (>=2.2.0) ; extra == 'tensorflow'
Provides-Extra: tensorflow_gpu
Requires-Dist: tensorflow-gpu (>=2.2.0) ; extra == 'tensorflow_gpu'
Provides-Extra: tests
Requires-Dist: apache-beam ; extra == 'tests'
Requires-Dist: absl-py ; extra == 'tests'
Requires-Dist: bs4 ; extra == 'tests'
Requires-Dist: elasticsearch ; extra == 'tests'
Requires-Dist: faiss-cpu ; extra == 'tests'
Requires-Dist: langdetect ; extra == 'tests'
Requires-Dist: mwparserfromhell ; extra == 'tests'
Requires-Dist: nltk ; extra == 'tests'
Requires-Dist: pytest ; extra == 'tests'
Requires-Dist: pytest-xdist ; extra == 'tests'
Requires-Dist: tensorflow ; extra == 'tests'
Requires-Dist: torch ; extra == 'tests'
Requires-Dist: tldextract ; extra == 'tests'
Requires-Dist: zstandard ; extra == 'tests'
Provides-Extra: torch
Requires-Dist: torch ; extra == 'torch'
